.gitignore
MANIFEST.in
README.rst
setup.cfg
setup.py
docs/HISTORY.txt
docs/LICENSE.GPL
docs/LICENSE.txt
docs/MANUAL.txt
raptus/__init__.py
raptus.article.lightboxgallery.egg-info/PKG-INFO
raptus.article.lightboxgallery.egg-info/SOURCES.txt
raptus.article.lightboxgallery.egg-info/dependency_links.txt
raptus.article.lightboxgallery.egg-info/entry_points.txt
raptus.article.lightboxgallery.egg-info/namespace_packages.txt
raptus.article.lightboxgallery.egg-info/not-zip-safe
raptus.article.lightboxgallery.egg-info/requires.txt
raptus.article.lightboxgallery.egg-info/top_level.txt
raptus/article/__init__.py
raptus/article/lightboxgallery/__init__.py
raptus/article/lightboxgallery/configure.zcml
raptus/article/lightboxgallery/browser/__init__.py
raptus/article/lightboxgallery/browser/configure.zcml
raptus/article/lightboxgallery/browser/lightboxgallery.gif
raptus/article/lightboxgallery/browser/lightboxgallery.init.js
raptus/article/lightboxgallery/browser/lightboxgallery.pt
raptus/article/lightboxgallery/browser/lightboxgallery.py
raptus/article/lightboxgallery/i18n/raptus.article-de.mo
raptus/article/lightboxgallery/i18n/raptus.article-de.po
raptus/article/lightboxgallery/i18n/raptus.article-fr.mo
raptus/article/lightboxgallery/i18n/raptus.article-fr.po
raptus/article/lightboxgallery/i18n/raptus.article.pot
raptus/article/lightboxgallery/profiles/default/cssregistry.xml
raptus/article/lightboxgallery/profiles/default/jsregistry.xml
raptus/article/lightboxgallery/profiles/default/metadata.xml
raptus/article/lightboxgallery/profiles/default/propertiestool.xml
raptus/article/lightboxgallery/profiles/default/skins.xml
raptus/article/lightboxgallery/profiles/default/viewlets.xml
raptus/article/lightboxgallery/skins/raptus_article_lightboxgallery/raptus.article.lightboxgallery.css.dtml