Metadata-Version: 1.1
Name: raptus.article.lightboxgallery
Version: 2.0b8
Summary: Provides an inline lightbox component with a horizontal gallery showing the images contained in the article.
Home-page: https://github.com/Raptus/raptus.article.lightboxgallery
Author: Raptus AG
Author-email: dev@raptus.com
License: GPL
Platform: UNKNOWN
Classifier: Programming Language :: Python
Classifier: Topic :: Software Development :: Libraries :: Python Modules
